[
    {
      "title": "Título del primer video",
      "content": "Descripción del primer video",
      "url": "https://www.youtube.com/embed/OyNA4FA47do?si=8WjHqQUZaxD8BlZi"
    },
    {
      "title": "Título del segundo video",
      "content": "Descripción del segundo video",
      "url": "https://www.youtube.com/embed/mzpCCqKBgWw?si=LiXC-2tx1lQGJCVa"
    },
    {
      "title": "Título del tercer video",
      "content": "Descripción del tercer video",
      "url": "https://www.youtube.com/embed/pKoH9GkEKxQ?si=Q1OdLc8rdyi9zx_9"
    }
  ]
  